guruguru/__init__.py
guruguru/authentication.py
guruguru/cli.py
guruguru/client.py
guruguru/competitions.py
guruguru/constance.py
guruguru/submissions.py
guruguru/utils.py
guruguru/version.py
tests/__init__.py
tests/conftest.py
tests/test_authentication.py
tests/test_cli.py
tests/test_client.py
tests/test_competitions.py
tests/test_constance.py
tests/test_submissions.py
tests/test_utils.py
guruguru-0.1.2.1.dist-info/METADATA
guruguru-0.1.2.1.dist-info/WHEEL
guruguru-0.1.2.1.dist-info/entry_points.txt
guruguru-0.1.2.1.dist-info/top_level.txt
guruguru-0.1.2.1.dist-info/RECORD
